LICENSE
MANIFEST.in
README.rst
setup.py
django_epic_sample.egg-info/PKG-INFO
django_epic_sample.egg-info/SOURCES.txt
django_epic_sample.egg-info/dependency_links.txt
django_epic_sample.egg-info/entry_points.txt
django_epic_sample.egg-info/requires.txt
django_epic_sample.egg-info/top_level.txt
epic_sample/__init__.py
epic_sample/db.sqlite3
epic_sample/manage.py
epic_sample/epic-sample/__init__.py
epic_sample/epic-sample/settings.py
epic_sample/epic-sample/urls.py
epic_sample/epic-sample/wsgi.py
epic_sample/epic-sample/static/bootstrap-3.3.2-dist/css/bootstrap-theme.css
epic_sample/epic-sample/static/bootstrap-3.3.2-dist/css/bootstrap-theme.css.map
epic_sample/epic-sample/static/bootstrap-3.3.2-dist/css/bootstrap-theme.min.css
epic_sample/epic-sample/static/bootstrap-3.3.2-dist/css/bootstrap.css
epic_sample/epic-sample/static/bootstrap-3.3.2-dist/css/bootstrap.css.map
epic_sample/epic-sample/static/bootstrap-3.3.2-dist/css/bootstrap.min.css
epic_sample/epic-sample/static/bootstrap-3.3.2-dist/fonts/glyphicons-halflings-regular.eot
epic_sample/epic-sample/static/bootstrap-3.3.2-dist/fonts/glyphicons-halflings-regular.svg
epic_sample/epic-sample/static/bootstrap-3.3.2-dist/fonts/glyphicons-halflings-regular.ttf
epic_sample/epic-sample/static/bootstrap-3.3.2-dist/fonts/glyphicons-halflings-regular.woff
epic_sample/epic-sample/static/bootstrap-3.3.2-dist/fonts/glyphicons-halflings-regular.woff2
epic_sample/epic-sample/static/bootstrap-3.3.2-dist/js/bootstrap.js
epic_sample/epic-sample/static/bootstrap-3.3.2-dist/js/bootstrap.min.js
epic_sample/epic-sample/static/bootstrap-3.3.2-dist/js/npm.js
epic_sample/epic-sample/static/bootstrap-table-1.12.1/bootstrap-table.min.css
epic_sample/epic-sample/static/bootstrap-table-1.12.1/bootstrap-table.min.js
epic_sample/epic-sample/static/bootstrap/css/bootstrap-theme.css
epic_sample/epic-sample/static/bootstrap/css/bootstrap-theme.css.map
epic_sample/epic-sample/static/bootstrap/css/bootstrap-theme.min.css
epic_sample/epic-sample/static/bootstrap/css/bootstrap.css
epic_sample/epic-sample/static/bootstrap/css/bootstrap.css.map
epic_sample/epic-sample/static/bootstrap/css/bootstrap.min.css
epic_sample/epic-sample/static/bootstrap/fonts/glyphicons-halflings-regular.eot
